pewsql/__init__.py
pewsql/correlation.py
pewsql-0.0.1.dist-info/DESCRIPTION.rst
pewsql-0.0.1.dist-info/METADATA
pewsql-0.0.1.dist-info/RECORD
pewsql-0.0.1.dist-info/WHEEL
pewsql-0.0.1.dist-info/metadata.json
pewsql-0.0.1.dist-info/top_level.txt
