Metadata-Version: 2.0
Name: pewsql
Version: 0.0.1
Summary: Analytics Tools for RDBMS
Home-page: UNKNOWN
Author: anderson
Author-email: a141890@gmail.com
License: UNKNOWN
Keywords: sql,analytics
Platform: UNKNOWN
Classifier: Intended Audience :: Science/Research
Classifier: Intended Audience :: System Administrators
Classifier: Topic :: Database
Classifier: Topic :: Scientific/Engineering
Classifier: Topic :: Scientific/Engineering :: Information Analysis
Requires-Python: >=3
Requires-Dist: numpy
Requires-Dist: pandas
Requires-Dist: pony
Requires-Dist: psycopg2
